StaICC/__init__.py
StaICC/diagnosis.py
StaICC/normal.py
StaICC/cached_dataset/__init__.py
StaICC/cached_dataset/agnews.dataset
StaICC/cached_dataset/financial_phrasebank.dataset
StaICC/cached_dataset/hate_speech_18.dataset
StaICC/cached_dataset/rotten_tomatoes.dataset
StaICC/cached_dataset/sst2.dataset
StaICC/cached_dataset/sst5.dataset
StaICC/cached_dataset/subjective.dataset
StaICC/cached_dataset/trec.dataset
StaICC/cached_dataset/tweet_eval_emotion.dataset
StaICC/cached_dataset/tweet_eval_hate.dataset
StaICC/prefabricate_inference/__init__.py
StaICC/prefabricate_inference/model_kernel.py
StaICC/prefabricate_inference/prompt_template_edit.py
StaICC/prefabricate_inference/standard_calibration.py
StaICC/util/__init__.py
StaICC/util/configs.py
StaICC/util/dataset_interface.py
StaICC/util/experimentor.py
StaICC/util/functional.py
StaICC/util/hgf_dataset_loader.py
StaICC/util/stable_random.py
StaICC-0.1.1.dist-info/METADATA
StaICC-0.1.1.dist-info/WHEEL
StaICC-0.1.1.dist-info/top_level.txt
StaICC-0.1.1.dist-info/RECORD
