Metadata-Version: 2.2
Name: StaICC
Version: 0.1.1
Summary: A standardized toolkit for classification task on In-context Learning.
Home-page: https://github.com/hc495/StaICC
Author: Hakaze Cho
Author-email: yfzhao@jaist.ac.jp
Classifier: Programming Language :: Python :: 3
Classifier: License :: OSI Approved :: Apache Software License
Dynamic: author
Dynamic: author-email
Dynamic: classifier
Dynamic: description
Dynamic: description-content-type
Dynamic: home-page
Dynamic: summary
